odoo/addons/easy_my_coop_payment_term/README.rst
odoo/addons/easy_my_coop_payment_term/__init__.py
odoo/addons/easy_my_coop_payment_term/__manifest__.py
odoo/addons/easy_my_coop_payment_term/i18n/easy_my_coop_payment_term.pot
odoo/addons/easy_my_coop_payment_term/models/__init__.py
odoo/addons/easy_my_coop_payment_term/models/company.py
odoo/addons/easy_my_coop_payment_term/models/subscription_request.py
odoo/addons/easy_my_coop_payment_term/readme/CONTRIBUTORS.rst
odoo/addons/easy_my_coop_payment_term/readme/DESCRIPTION.rst
odoo/addons/easy_my_coop_payment_term/static/description/index.html
odoo/addons/easy_my_coop_payment_term/views/res_company_view.xml
odoo12_addon_easy_my_coop_payment_term-12.0.1.0.0.99.dev5.dist-info/METADATA
odoo12_addon_easy_my_coop_payment_term-12.0.1.0.0.99.dev5.dist-info/WHEEL
odoo12_addon_easy_my_coop_payment_term-12.0.1.0.0.99.dev5.dist-info/top_level.txt
odoo12_addon_easy_my_coop_payment_term-12.0.1.0.0.99.dev5.dist-info/RECORD
